LICENSE
README.md
setup.py
HiveNetConsole/__init__.py
HiveNetConsole/base_cmd.py
HiveNetConsole/server.py
HiveNetConsole.egg-info/PKG-INFO
HiveNetConsole.egg-info/SOURCES.txt
HiveNetConsole.egg-info/dependency_links.txt
HiveNetConsole.egg-info/not-zip-safe
HiveNetConsole.egg-info/requires.txt
HiveNetConsole.egg-info/top_level.txt
HiveNetConsole/conf/__init__.py
HiveNetConsole/i18n/__init__.py
HiveNetConsole/i18n/message_zh_cn.json